impressionismcat/__init__.py
impressionismcat/__version__.py
impressionismcat/paint/__init__.py
impressionismcat/paint/style.py
impressionismcat-0.0.2.dist-info/LICENSE
impressionismcat-0.0.2.dist-info/METADATA
impressionismcat-0.0.2.dist-info/WHEEL
impressionismcat-0.0.2.dist-info/top_level.txt
impressionismcat-0.0.2.dist-info/RECORD
