Metadata-Version: 2.1
Name: impressionismcat
Version: 0.0.2
Summary: ImpressionismCat, A Cat Full of Imagination.
Home-page: https://github.com/Ewen2015/ImpressionismCat
Author: Ewen Wang
Author-email: wolfgangwong2012@gmail.com
License: MIT License
Classifier: License :: OSI Approved :: MIT License
Classifier: Programming Language :: Python :: 3.8
License-File: LICENSE
Requires-Dist: pandas
Requires-Dist: numpy
Requires-Dist: matplotlib
Requires-Dist: tensorflow
